dataflows_elasticsearch/VERSION
dataflows_elasticsearch/__init__.py
dataflows_elasticsearch/processors/__init__.py
dataflows_elasticsearch/processors/dump_to_elasticsearch.py
dataflows_elasticsearch-0.1.2.dist-info/LICENSE.md
dataflows_elasticsearch-0.1.2.dist-info/METADATA
dataflows_elasticsearch-0.1.2.dist-info/WHEEL
dataflows_elasticsearch-0.1.2.dist-info/top_level.txt
dataflows_elasticsearch-0.1.2.dist-info/RECORD
