Metadata-Version: 2.1
Name: dataflows-elasticsearch
Version: 0.1.2
Summary: A utility library for working with data flows in Python and ElasticSearch
Home-page: https://github.com/dataspot/dataflows-elasticsearch
Author: Adam Kariv
Author-email: adam.kariv@gmail.com
License: MIT
Keywords: frictionless data,open data,json schema,table schema,data package,tabular data package
Classifier: Development Status :: 4 - Beta
Classifier: Environment :: Web Environment
Classifier: Intended Audience :: Developers
Classifier: License :: OSI Approved :: MIT License
Classifier: Operating System :: OS Independent
Classifier: Programming Language :: Python :: 3.7
Classifier: Topic :: Internet :: WWW/HTTP :: Dynamic Content
Classifier: Topic :: Software Development :: Libraries :: Python Modules
License-File: LICENSE.md
Requires-Dist: six
Requires-Dist: dataflows
Requires-Dist: tableschema-elasticsearch >=2
Provides-Extra: develop
Requires-Dist: moto[server] ; extra == 'develop'
Requires-Dist: pytest-cov ; extra == 'develop'
Requires-Dist: pytest ; extra == 'develop'
Requires-Dist: pylama ; extra == 'develop'
Requires-Dist: mock ; extra == 'develop'
Requires-Dist: tox ; extra == 'develop'
